{
  "heading": {
    "render": "Heading"

  },
  "paragraph": {
    "render": "Paragraph"
  },
  "link": {
    "render": "Link"
  },
  "list": {
    "render": "Item 1\nItem 2"
  },
	"image": {
    "render": "/images/picture.png"
  },
 "input_box": {
    "render": "Input Box"
  },
  "textarea": {
    "render": "Textarea"
  },
  "check_box": {
    "render": "Change Me\nChange Me Too"
  },
  "radio_buttons": {
    "render": "Change\nUs"
  },
  "table": {
    "render": "Change\nValues"
  },
  "submit_button": {
    "render": "Submit"
  },
  "select_menu": {
     "render": "Choose One"
	},
	"global_container": {
		"render": "Drop More Items in Here"
	},
	"main_navigation": {
		"render": "Nav item 1\nNav item 2\nNav item 3"
	},
	"user_navigation": {
		"render": "Nav item 1\nNav item 2\nNav item 3"
	},
	"footer_navigation": {
		"render": "Nav item 1\nNav item 2\nNav item 3"
	},
	"box_container": {
		"render": ""
	},
	"vertical_line": {
		"render": "" 
	},
	"horizontal_line": {
		"render": "" 
	}
}
